{
    "name": "Briefing Diario AI [ArcelorMittal] UPDATE",
    "nodes": [
        {
            "parameters": {
                "rule": {
                    "interval": [
                        {
                            "field": "cronExpression",
                            "expression": "0 6 * * 1-5"
                        }
                    ]
                }
            },
            "id": "trigger-schedule",
            "name": "Acionar",
            "type": "n8n-nodes-base.scheduleTrigger",
            "typeVersion": 1,
            "position": [
                200,
                300
            ]
        },
        {
            "parameters": {
                "jsCode": "// DATA SEGURA\nconst now = new Date();\nconst brFormatter = new Intl.DateTimeFormat('en-CA', { timeZone: 'America/Sao_Paulo' });\nconst hojeStr = brFormatter.format(now);\nconst hojeDate = new Date(hojeStr + 'T12:00:00');\n\nconst ontemDate = new Date(hojeDate);\nontemDate.setDate(ontemDate.getDate() - 1);\n\nconst dataOntem = ontemDate.toISOString().split('T')[0];\nconst inicioMes = hojeStr.substring(0, 7) + '-01';\n\nconst mesAtual = hojeDate.getMonth();\nconst monthRef = hojeStr.substring(0, 7);\n\nconst supabaseUrl = 'https://tyrxbarucopizpcalooh.supabase.co';\nconst supabaseKey = 'eyJhbGciOiJIUzI1NiIsInR5cCI6IkpXVCJ9.eyJpc3MiOiJzdXBhYmFzZSIsInJlZiI6InR5cnhiYXJ1Y29waXpwY2Fsb29oIiwicm9sZSI6ImFub24iLCJpYXQiOjE3NTIwMDQ0OTUsImV4cCI6MjA2NzU4MDQ5NX0.ycJzhslzMyD0DQWWu5hY09SucH94OTwWI60oIqm-EB8';\nconst headers = { 'apikey': supabaseKey, 'Authorization': 'Bearer ' + supabaseKey };\n\nconst ORCAMENTO = [\n  { month: 0, producao: 17118.27, energia: 80.76, gas: 45.40 },\n  { month: 1, producao: 20400, energia: 75.00, gas: 41.95 },\n  { month: 2, producao: 23000, energia: 75.00, gas: 41.83 },\n  { month: 3, producao: 21800, energia: 75.00, gas: 42.08 },\n  { month: 4, producao: 22300, energia: 75.00, gas: 41.83 },\n  { month: 5, producao: 11200, energia: 75.00, gas: 41.50 },\n  { month: 6, producao: 11400, energia: 75.00, gas: 42.43 },\n  { month: 7, producao: 22500, energia: 75.00, gas: 41.00 },\n  { month: 8, producao: 21500, energia: 75.00, gas: 40.00 },\n  { month: 9, producao: 22000, energia: 75.00, gas: 39.00 },\n  { month: 10, producao: 21300, energia: 73.00, gas: 38.00 },\n  { month: 11, producao: 22000, energia: 72.00, gas: 38.00 }\n];\nconst budgetMes = ORCAMENTO.find(b => b.month === mesAtual) || ORCAMENTO[1];\n\nlet historicoMes = [];\nlet justificativas = [];\n\ntry {\n  const [hResp, jResp] = await Promise.all([\n    this.helpers.httpRequest({ method: 'GET', url: supabaseUrl + '/rest/v1/diario_bordo_real?data=gte.' + inicioMes + '&data=lte.' + dataOntem + '&order=data.asc', headers }),\n    this.helpers.httpRequest({ method: 'GET', url: supabaseUrl + '/rest/v1/kpi_justifications?month_ref=eq.' + monthRef, headers })\n  ]);\n  historicoMes = Array.isArray(hResp) ? hResp : [];\n  justificativas = Array.isArray(jResp) ? jResp : [];\n} catch(e) {\n  historicoMes = $('Get Forecast Ontem').all().map(i => i.json);\n}\n\nconst recOntem = historicoMes.find(r => r.data === dataOntem) || historicoMes[historicoMes.length - 1] || {};\nconst justMap = {};\njustificativas.forEach(j => { justMap[j.kpi_type] = j.justification; });\n\nconst acumProd = historicoMes.reduce((s, r) => s + (parseFloat(r.producao_laminacao) || 0), 0);\nconst acumGasRaw = historicoMes.reduce((s, r) => s + (parseFloat(r.consumo_gas_tl01) || 0), 0);\nconst acumEe = historicoMes.reduce((s, r) => s + (parseFloat(r.consumo_energia_total) || 0), 0);\n\nlet totalFatorPCS = 0, countFatorPCS = 0;\nhistoricoMes.forEach(r => { const f = parseFloat(r.fator_pcs); if (!isNaN(f) && f > 0) { totalFatorPCS += f; countFatorPCS++; } });\nconst fatorPCS = countFatorPCS > 0 ? totalFatorPCS / countFatorPCS : 1;\nconst acumGas = acumGasRaw * fatorPCS;\n\nconst prodDia = parseFloat(recOntem.producao_laminacao) || 0;\nconst gasDia = (parseFloat(recOntem.consumo_gas_tl01) || 0) * fatorPCS;\nconst eeDia = parseFloat(recOntem.consumo_energia_total) || 0;\n\nconst gasEspecDia = prodDia > 0 ? gasDia / prodDia : 0;\nconst eeEspecDia = prodDia > 0 ? eeDia / prodDia : 0;\n\nconst gasEspecAcum = acumProd > 0 ? acumGas / acumProd : 0;\nconst eeEspecAcum = acumProd > 0 ? acumEe / acumProd : 0;\n\n// PREVISAO: FONTE UNICA = tabela forecast_cache no Supabase\nlet previsaoProducao = 0;\nlet previsaoGnEspec = 0;\nlet previsaoEeEspec = 0;\nlet forecastDebug = 'buscando forecast_cache';\n\ntry {\n  const cacheResp = await this.helpers.httpRequest({\n    method: 'GET',\n    url: supabaseUrl + '/rest/v1/forecast_cache?id=eq.current&select=previsao_fechamento,previsao_gas,previsao_energia,updated_at',\n    headers\n  });\n  \n  if (Array.isArray(cacheResp) && cacheResp.length > 0 && cacheResp[0].previsao_fechamento > 0) {\n    previsaoProducao = Math.round(cacheResp[0].previsao_fechamento);\n    previsaoGnEspec = cacheResp[0].previsao_gas || 0;\n    previsaoEeEspec = cacheResp[0].previsao_energia || 0;\n    forecastDebug = 'forecast_cache OK: ' + previsaoProducao + ' (at ' + cacheResp[0].updated_at + ')';\n  }\n} catch(e) {\n  forecastDebug = 'forecast_cache FALHOU: ' + (e.message || '').substring(0, 60);\n}\n\n// FALLBACK 1: API local\nif (previsaoProducao === 0) {\n  try {\n    const forecastResp = await this.helpers.httpRequest({ method: 'GET', url: 'http://127.0.0.1:3000/api/forecast', timeout: 3000 });\n    if (forecastResp && forecastResp.previsaoFechamento > 0) {\n      previsaoProducao = forecastResp.previsaoFechamento;\n      previsaoGnEspec = forecastResp.previsaoGas || 0;\n      previsaoEeEspec = forecastResp.previsaoEnergia || 0;\n      forecastDebug += ' | API local OK: ' + previsaoProducao;\n    }\n  } catch(e) { forecastDebug += ' | API local falhou'; }\n}\n\n// FALLBACK 2: PCP soma data final\nif (previsaoProducao === 0) {\n  try {\n    const fimMesStr2 = new Date(hojeDate.getFullYear(), mesAtual + 1, 1).toISOString().split('T')[0];\n    const pcpResp = await this.helpers.httpRequest({ method: 'GET', url: supabaseUrl + '/rest/v1/pcp_data?select=producao_planejada&inicio=gte.' + inicioMes + 'T00:00:00&inicio=lt.' + fimMesStr2 + 'T00:00:00', headers });\n    const pcpAll = Array.isArray(pcpResp) ? pcpResp : [];\n    const soma = pcpAll.reduce((s, r) => s + (parseFloat(r.producao_planejada) || 0), 0);\n    if (soma > 0) { previsaoProducao = Math.round(soma); forecastDebug += ' | PCP soma: ' + previsaoProducao; }\n  } catch(e2) { forecastDebug += ' | PCP falhou'; }\n}\n\n// FALLBACK 3: Regra de tres (Linear)\nif (previsaoProducao === 0) {\n  const diaRef = hojeDate.getDate() - 1;\n  const totalDias = new Date(hojeDate.getFullYear(), hojeDate.getMonth() + 1, 0).getDate();\n  previsaoProducao = diaRef > 0 ? Math.round((acumProd / diaRef) * totalDias) : Math.round(acumProd);\n  forecastDebug += ' | Linear: ' + previsaoProducao;\n}\n\nif (previsaoGnEspec === 0) previsaoGnEspec = gasEspecAcum;\nif (previsaoEeEspec === 0) previsaoEeEspec = eeEspecAcum;\n\nconst fimMesStr = new Date(hojeDate.getFullYear(), mesAtual + 1, 1).toISOString().split('T')[0];\nlet pcpMes = [];\ntry {\n  const pcpFamResp = await this.helpers.httpRequest({ method: 'GET', url: supabaseUrl + '/rest/v1/pcp_data?select=familia,inicio&and=(inicio.gte.' + inicioMes + 'T00:00:00,inicio.lt.' + fimMesStr + 'T00:00:00)&order=inicio.asc&limit=500', headers });\n  pcpMes = Array.isArray(pcpFamResp) ? pcpFamResp : [];\n} catch(e) {}\n\nfunction simplificarFamilia(fam) {\n  const f = (fam || '').toUpperCase().trim();\n  if (f.includes('CHATO MOLA')) return 'Barra Chata Mola';\n  if (f.includes('CHATO')) return 'Barra Chata';\n  if (f.includes('CANTONEIRA')) return 'Cantoneira';\n  if (f.includes('REDONDA')) return 'Barra Redonda';\n  if (f.includes('VIGA I')) return 'Viga I';\n  if (f.includes('VIGA U')) return 'Viga U';\n  if (f.includes('TRILHO')) return 'Trilho';\n  if (f.includes('PERFIL')) return 'Perfil';\n  return f || 'Outros';\n}\n\nconst pcpDia = pcpMes.filter(p => (p.inicio || '').split('T')[0] === dataOntem);\nconst familiasTexto = [...new Set(pcpDia.map(p => simplificarFamilia(p.familia)).filter(f => f !== 'Outros'))].join(', ') || 'Nao identificado';\n\nconst dataFormatada = dataOntem.split('-').reverse().join('/');\nconst fmt = (n) => Number(n).toFixed(2).replace('.', ',');\nconst fmtInt = (n) => Math.round(Number(n)).toString();\n\nconst prompt = 'Crie um resumo diario em texto corrido, SEM asteriscos, SEM negrito, SEM emojis, SEM markdown. Destinado a diretoria.\\n\\nREGRAS:\\n1. Diga sempre dia anterior ou fechamento do dia. Nunca turno anterior.\\n2. Nunca use T isolado. Escreva toneladas por extenso.\\n3. Gas natural: metro cubico por tonelada.\\n4. Energia eletrica: quilowatt-hora por tonelada.\\n5. Seja direto. Se houver justificativa para um KPI, inclua naturalmente.\\n6. INICIE COM:\\n\\nBom dia. Este e o nosso briefing diario com o balanco do fechamento do dia ' + dataFormatada + '.\\n\\nDados de producao:\\nAcumulado do mes: ' + fmt(acumProd) + ' toneladas.\\nProducao do dia anterior: ' + fmtInt(prodDia) + ' toneladas.\\nPrevisao de fechamento do mes: ' + fmtInt(previsaoProducao) + ' toneladas (orcamento: ' + fmtInt(budgetMes.producao) + ' toneladas).\\n' + (justMap.producao ? 'Nota: ' + justMap.producao : '') + '\\n\\nGas natural:\\nConsumo especifico acumulado: ' + fmt(gasEspecAcum) + ' m3 por tonelada.\\nConsumo especifico do dia anterior: ' + fmt(gasEspecDia) + ' m3 por tonelada.\\nPrevisao de fechamento: ' + fmt(previsaoGnEspec) + ' m3 por tonelada.\\n' + (justMap.gas ? 'Nota: ' + justMap.gas : '') + '\\n\\nEnergia eletrica:\\nConsumo especifico acumulado: ' + fmt(eeEspecAcum) + ' kWh por tonelada.\\nConsumo especifico do dia anterior: ' + fmt(eeEspecDia) + ' kWh por tonelada.\\nPrevisao de fechamento: ' + fmt(previsaoEeEspec) + ' kWh por tonelada.\\n' + (justMap.energia ? 'Nota: ' + justMap.energia : '') + '\\n\\nAgradeco a atencao. Sigamos focados.';\n\nreturn [{\n  json: {\n    prompt,\n    dataRef: dataFormatada,\n    dataISO: dataOntem,\n    material: familiasTexto,\n    producao: { acumulada: fmt(acumProd), dia: fmtInt(prodDia), previsao: fmtInt(previsaoProducao), orcamento: fmtInt(budgetMes.producao), justificativa: justMap.producao || '' },\n    gn: { acumEspec: fmt(gasEspecAcum), especDia: fmt(gasEspecDia), previsao: fmt(previsaoGnEspec), fatorPCS: fatorPCS.toFixed(6), justificativa: justMap.gas || '' },\n    ee: { acumEspec: fmt(eeEspecAcum), especDia: fmt(eeEspecDia), previsao: fmt(previsaoEeEspec), justificativa: justMap.energia || '' },\n    debug: { hojeStr, dataOntem, diasHistorico: historicoMes.length, forecastAPI: forecastDebug }\n  }\n}];"
            },
            "id": "node-prompt-ia",
            "name": "Montar Prompt IA",
            "type": "n8n-nodes-base.code",
            "typeVersion": 2,
            "position": [
                400,
                300
            ]
        }
    ],
    "connections": {
        "Acionar": {
            "main": [
                [
                    {
                        "node": "Montar Prompt IA",
                        "type": "main",
                        "index": 0
                    }
                ]
            ]
        }
    }
}